mkdocs_gemini_chatbot/__init__.py
mkdocs_gemini_chatbot/plugin.py
mkdocs_gemini_chatbot/templates/chatbot.css
mkdocs_gemini_chatbot/templates/chatbot.js
mkdocs_gemini_chatbot-1.0.1.dist-info/licenses/LICENSE
mkdocs_gemini_chatbot-1.0.1.dist-info/METADATA
mkdocs_gemini_chatbot-1.0.1.dist-info/WHEEL
mkdocs_gemini_chatbot-1.0.1.dist-info/entry_points.txt
mkdocs_gemini_chatbot-1.0.1.dist-info/top_level.txt
mkdocs_gemini_chatbot-1.0.1.dist-info/RECORD
