Metadata-Version: 2.4
Name: mkdocs-gemini-chatbot
Version: 1.0.1
Summary: A MkDocs plugin to add a Gemini-powered chatbot to your documentation site.
Author-email: Massimiliano Falzari <massimiliano@falzari.dev>
License: MIT
Project-URL: Homepage, https://github.com/vimmoos/mkdocs-gemini-chatbot.git
Project-URL: Repository, https://github.com/vimmoos/mkdocs-gemini-chatbot.git
Classifier: License :: OSI Approved :: MIT License
Classifier: Programming Language :: Python :: 3
Classifier: Programming Language :: Python :: 3.8
Classifier: Programming Language :: Python :: 3.9
Classifier: Programming Language :: Python :: 3.10
Classifier: Programming Language :: Python :: 3.11
Classifier: Operating System :: OS Independent
Classifier: Intended Audience :: Developers
Classifier: Topic :: Documentation
Classifier: Topic :: Software Development :: Documentation
Requires-Python: >=3.8
License-File: LICENSE
Requires-Dist: mkdocs>=1.4
Requires-Dist: beautifulsoup4
Requires-Dist: python-dotenv
Dynamic: license-file
